{
  "marks2": [
    {
      "REGNO": "202216002",
      "INT": 20.35,
      "UM": 20.25,
      "TOT": 41.0,
      "GRADE": "E",
      "SUBJECT": "CA1106A WEB DEVELOPMENT USING PHP"
    },
    {
      "REGNO": "202216003",
      "INT": 41.5,
      "UM": 39.5,
      "TOT": 81.0,
      "GRADE": "A",
      "SUBJECT": "CA1106A WEB DEVELOPMENT USING PHP"
    },
    {
      "REGNO": "202216004",
      "INT": 34.3,
      "UM": 46.75,
      "TOT": 82.0,
      "GRADE": "S",
      "SUBJECT": "CA1106A WEB DEVELOPMENT USING PHP"
    },
    {
      "REGNO": "202216005",
      "INT": 28.45,
      "UM": 14.25,
      "TOT": 43.0,
      "GRADE": "E",
      "SUBJECT": "CA1106A WEB DEVELOPMENT USING PHP"
    },
    {
      "REGNO": "202216007",
      "INT": 36.05,
      "UM": 43.25,
      "TOT": 80.0,
      "GRADE": "A",
      "SUBJECT": "CA1106A WEB DEVELOPMENT USING PHP"
    },
    {
      "REGNO": "202216008",
      "INT": 19.25,
      "UM": 9.0,
      "TOT": 29.0,
      "GRADE": "F",
      "SUBJECT": "CA1106A WEB DEVELOPMENT USING PHP"
    },
    {
      "REGNO": "202216009",
      "INT": 12.75,
      "UM": 5.0,
      "TOT": 18.0,
      "GRADE": "F",
      "SUBJECT": "CA1106A WEB DEVELOPMENT USING PHP"
    },
    {
      "REGNO": "202216010",
      "INT": 26.3,
      "UM": 19.75,
      "TOT": 47.0,
      "GRADE": "D",
      "SUBJECT": "CA1106A WEB DEVELOPMENT USING PHP"
    },
    {
      "REGNO": "202216011",
      "INT": 39.4,
      "UM": 48.0,
      "TOT": 88.0,
      "GRADE": "S",
      "SUBJECT": "CA1106A WEB DEVELOPMENT USING PHP"
    },
    {
      "REGNO": "202216012",
      "INT": 20.35,
      "UM": 15.5,
      "TOT": 36.0,
      "GRADE": "E",
      "SUBJECT": "CA1106A WEB DEVELOPMENT USING PHP"
    },
    {
      "REGNO": "202216013",
      "INT": 28.1,
      "UM": 23.25,
      "TOT": 52.0,
      "GRADE": "D",
      "SUBJECT": "CA1106A WEB DEVELOPMENT USING PHP"
    },
    {
      "REGNO": "202216015",
      "INT": 19.65,
      "UM": 15.0,
      "TOT": 35.0,
      "GRADE": "E",
      "SUBJECT": "CA1106A WEB DEVELOPMENT USING PHP"
    },
    {
      "REGNO": "202216016",
      "INT": 0.0,
      "UM": "DT",
      "TOT": 0.0,
      "GRADE": "DT",
      "SUBJECT": "CA1106A WEB DEVELOPMENT USING PHP"
    },
    {
      "REGNO": "202216017",
      "INT": 21.7,
      "UM": 24.75,
      "TOT": 47.0,
      "GRADE": "D",
      "SUBJECT": "CA1106A WEB DEVELOPMENT USING PHP"
    },
    {
      "REGNO": "202216018",
      "INT": 21.6,
      "UM": 15.75,
      "TOT": 38.0,
      "GRADE": "E",
      "SUBJECT": "CA1106A WEB DEVELOPMENT USING PHP"
    },
    {
      "REGNO": "202216019",
      "INT": 16.5,
      "UM": 10.25,
      "TOT": 27.0,
      "GRADE": "F",
      "SUBJECT": "CA1106A WEB DEVELOPMENT USING PHP"
    },
    {
      "REGNO": "202216020",
      "INT": 18.4,
      "UM": 16.75,
      "TOT": 36.0,
      "GRADE": "E",
      "SUBJECT": "CA1106A WEB DEVELOPMENT USING PHP"
    },
    {
      "REGNO": "202216022",
      "INT": 35.5,
      "UM": 26.0,
      "TOT": 62.0,
      "GRADE": "C",
      "SUBJECT": "CA1106A WEB DEVELOPMENT USING PHP"
    },
    {
      "REGNO": "202216023",
      "INT": 0.0,
      "UM": "DT",
      "TOT": 0.0,
      "GRADE": "DT",
      "SUBJECT": "CA1106A WEB DEVELOPMENT USING PHP"
    },
    {
      "REGNO": "202216024",
      "INT": 42.6,
      "UM": 39.0,
      "TOT": 82.0,
      "GRADE": "S",
      "SUBJECT": "CA1106A WEB DEVELOPMENT USING PHP"
    },
    {
      "REGNO": "202216025",
      "INT": 30.15,
      "UM": 26.75,
      "TOT": 57.0,
      "GRADE": "C",
      "SUBJECT": "CA1106A WEB DEVELOPMENT USING PHP"
    },
    {
      "REGNO": "202216026",
      "INT": 33.55,
      "UM": 25.75,
      "TOT": 60.0,
      "GRADE": "C",
      "SUBJECT": "CA1106A WEB DEVELOPMENT USING PHP"
    },
    {
      "REGNO": "202216027",
      "INT": 35.65,
      "UM": 20.0,
      "TOT": 56.0,
      "GRADE": "C",
      "SUBJECT": "CA1106A WEB DEVELOPMENT USING PHP"
    },
    {
      "REGNO": "202216028",
      "INT": 36.55,
      "UM": 34.25,
      "TOT": 71.0,
      "GRADE": "B",
      "SUBJECT": "CA1106A WEB DEVELOPMENT USING PHP"
    },
    {
      "REGNO": "202216031",
      "INT": 43.65,
      "UM": 48.5,
      "TOT": 93.0,
      "GRADE": "S",
      "SUBJECT": "CA1106A WEB DEVELOPMENT USING PHP"
    },
    {
      "REGNO": "202216032",
      "INT": 35.15,
      "UM": 31.75,
      "TOT": 67.0,
      "GRADE": "B",
      "SUBJECT": "CA1106A WEB DEVELOPMENT USING PHP"
    },
    {
      "REGNO": "202216034",
      "INT": 21.5,
      "UM": 18.5,
      "TOT": 40.0,
      "GRADE": "E",
      "SUBJECT": "CA1106A WEB DEVELOPMENT USING PHP"
    },
    {
      "REGNO": "202216037",
      "INT": 16.9,
      "UM": 4.75,
      "TOT": 22.0,
      "GRADE": "F",
      "SUBJECT": "CA1106A WEB DEVELOPMENT USING PHP"
    },
    {
      "REGNO": "202216038",
      "INT": 25.05,
      "UM": 16.5,
      "TOT": 42.0,
      "GRADE": "E",
      "SUBJECT": "CA1106A WEB DEVELOPMENT USING PHP"
    },
    {
      "REGNO": "202216039",
      "INT": 46.35,
      "UM": 49.0,
      "TOT": 96.0,
      "GRADE": "S",
      "SUBJECT": "CA1106A WEB DEVELOPMENT USING PHP"
    },
    {
      "REGNO": "202216040",
      "INT": 40.25,
      "UM": 39.0,
      "TOT": 80.0,
      "GRADE": "A",
      "SUBJECT": "CA1106A WEB DEVELOPMENT USING PHP"
    },
    {
      "REGNO": "202216041",
      "INT": 32.3,
      "UM": 23.0,
      "TOT": 56.0,
      "GRADE": "C",
      "SUBJECT": "CA1106A WEB DEVELOPMENT USING PHP"
    },
    {
      "REGNO": "202216042",
      "INT": 30.05,
      "UM": 21.25,
      "TOT": 52.0,
      "GRADE": "D",
      "SUBJECT": "CA1106A WEB DEVELOPMENT USING PHP"
    },
    {
      "REGNO": "202216044",
      "INT": 26.6,
      "UM": 19.0,
      "TOT": 46.0,
      "GRADE": "D",
      "SUBJECT": "CA1106A WEB DEVELOPMENT USING PHP"
    },
    {
      "REGNO": "202216045",
      "INT": 0.0,
      "UM": "DT",
      "TOT": 0.0,
      "GRADE": "DT",
      "SUBJECT": "CA1106A WEB DEVELOPMENT USING PHP"
    },
    {
      "REGNO": "202216046",
      "INT": 39.98,
      "UM": 42.0,
      "TOT": 82.0,
      "GRADE": "S",
      "SUBJECT": "CA1106A WEB DEVELOPMENT USING PHP"
    },
    {
      "REGNO": "202216047",
      "INT": 38.0,
      "UM": 18.5,
      "TOT": 57.0,
      "GRADE": "C",
      "SUBJECT": "CA1106A WEB DEVELOPMENT USING PHP"
    },
    {
      "REGNO": "202216048",
      "INT": 18.7,
      "UM": 4.5,
      "TOT": 24.0,
      "GRADE": "F",
      "SUBJECT": "CA1106A WEB DEVELOPMENT USING PHP"
    },
    {
      "REGNO": "202216049",
      "INT": 33.3,
      "UM": 27.5,
      "TOT": 61.0,
      "GRADE": "C",
      "SUBJECT": "CA1106A WEB DEVELOPMENT USING PHP"
    },
    {
      "REGNO": "202216051",
      "INT": 36.1,
      "UM": 28.0,
      "TOT": 65.0,
      "GRADE": "B",
      "SUBJECT": "CA1106A WEB DEVELOPMENT USING PHP"
    },
    {
      "REGNO": "202216052",
      "INT": 19.95,
      "UM": 18.0,
      "TOT": 38.0,
      "GRADE": "E",
      "SUBJECT": "CA1106A WEB DEVELOPMENT USING PHP"
    },
    {
      "REGNO": "202216053",
      "INT": 28.1,
      "UM": 34.5,
      "TOT": 63.0,
      "GRADE": "B",
      "SUBJECT": "CA1106A WEB DEVELOPMENT USING PHP"
    },
    {
      "REGNO": "202216054",
      "INT": 29.65,
      "UM": 18.5,
      "TOT": 49.0,
      "GRADE": "D",
      "SUBJECT": "CA1106A WEB DEVELOPMENT USING PHP"
    },
    {
      "REGNO": "202216055",
      "INT": 13.7,
      "UM": 11.5,
      "TOT": 26.0,
      "GRADE": "F",
      "SUBJECT": "CA1106A WEB DEVELOPMENT USING PHP"
    },
    {
      "REGNO": "202216056",
      "INT": 23.7,
      "UM": 13.0,
      "TOT": 37.0,
      "GRADE": "E",
      "SUBJECT": "CA1106A WEB DEVELOPMENT USING PHP"
    },
    {
      "REGNO": "202216057",
      "INT": 25.9,
      "UM": 24.0,
      "TOT": 50.0,
      "GRADE": "D",
      "SUBJECT": "CA1106A WEB DEVELOPMENT USING PHP"
    },
    {
      "REGNO": "202216058",
      "INT": 20.7,
      "UM": 17.0,
      "TOT": 38.0,
      "GRADE": "E",
      "SUBJECT": "CA1106A WEB DEVELOPMENT USING PHP"
    },
    {
      "REGNO": "202216059",
      "INT": 28.0,
      "UM": 32.0,
      "TOT": 60.0,
      "GRADE": "C",
      "SUBJECT": "CA1106A WEB DEVELOPMENT USING PHP"
    },
    {
      "REGNO": "202216060",
      "INT": 28.0,
      "UM": 20.5,
      "TOT": 49.0,
      "GRADE": "D",
      "SUBJECT": "CA1106A WEB DEVELOPMENT USING PHP"
    },
    {
      "REGNO": "202216061",
      "INT": 20.4,
      "UM": 20.0,
      "TOT": 41.0,
      "GRADE": "E",
      "SUBJECT": "CA1106A WEB DEVELOPMENT USING PHP"
    },
    {
      "REGNO": "202216062",
      "INT": 34.9,
      "UM": 26.5,
      "TOT": 62.0,
      "GRADE": "C",
      "SUBJECT": "CA1106A WEB DEVELOPMENT USING PHP"
    },
    {
      "REGNO": "202216063",
      "INT": 41.2,
      "UM": 38.5,
      "TOT": 80.0,
      "GRADE": "A",
      "SUBJECT": "CA1106A WEB DEVELOPMENT USING PHP"
    },
    {
      "REGNO": "202216064",
      "INT": 23.15,
      "UM": 22.5,
      "TOT": 46.0,
      "GRADE": "D",
      "SUBJECT": "CA1106A WEB DEVELOPMENT USING PHP"
    },
    {
      "REGNO": "202216065",
      "INT": 34.0,
      "UM": 37.5,
      "TOT": 72.0,
      "GRADE": "B",
      "SUBJECT": "CA1106A WEB DEVELOPMENT USING PHP"
    },
    {
      "REGNO": "202216066",
      "INT": 21.45,
      "UM": 28.0,
      "TOT": 50.0,
      "GRADE": "D",
      "SUBJECT": "CA1106A WEB DEVELOPMENT USING PHP"
    },
    {
      "REGNO": "202216067",
      "INT": 17.15,
      "UM": 17.5,
      "TOT": 35.0,
      "GRADE": "E",
      "SUBJECT": "CA1106A WEB DEVELOPMENT USING PHP"
    },
    {
      "REGNO": "202216068",
      "INT": 15.15,
      "UM": 9.0,
      "TOT": 25.0,
      "GRADE": "F",
      "SUBJECT": "CA1106A WEB DEVELOPMENT USING PHP"
    },
    {
      "REGNO": "202216069",
      "INT": 20.2,
      "UM": 6.0,
      "TOT": 27.0,
      "GRADE": "F",
      "SUBJECT": "CA1106A WEB DEVELOPMENT USING PHP"
    },
    {
      "REGNO": "202216071",
      "INT": 33.6,
      "UM": 28.5,
      "TOT": 63.0,
      "GRADE": "B",
      "SUBJECT": "CA1106A WEB DEVELOPMENT USING PHP"
    },
    {
      "REGNO": "202216072",
      "INT": 32.3,
      "UM": 27.0,
      "TOT": 60.0,
      "GRADE": "C",
      "SUBJECT": "CA1106A WEB DEVELOPMENT USING PHP"
    },
    {
      "REGNO": "202216073",
      "INT": 30.0,
      "UM": 22.0,
      "TOT": 52.0,
      "GRADE": "D",
      "SUBJECT": "CA1106A WEB DEVELOPMENT USING PHP"
    },
    {
      "REGNO": "202216074",
      "INT": 32.3,
      "UM": 31.0,
      "TOT": 64.0,
      "GRADE": "B",
      "SUBJECT": "CA1106A WEB DEVELOPMENT USING PHP"
    },
    {
      "REGNO": "202216076",
      "INT": 22.8,
      "UM": 31.0,
      "TOT": 54.0,
      "GRADE": "C",
      "SUBJECT": "CA1106A WEB DEVELOPMENT USING PHP"
    },
    {
      "REGNO": "202216077",
      "INT": 32.7,
      "UM": 24.0,
      "TOT": 57.0,
      "GRADE": "C",
      "SUBJECT": "CA1106A WEB DEVELOPMENT USING PHP"
    },
    {
      "REGNO": "202216078",
      "INT": 28.9,
      "UM": 27.5,
      "TOT": 57.0,
      "GRADE": "C",
      "SUBJECT": "CA1106A WEB DEVELOPMENT USING PHP"
    },
    {
      "REGNO": "202216079",
      "INT": 30.55,
      "UM": 31.5,
      "TOT": 63.0,
      "GRADE": "B",
      "SUBJECT": "CA1106A WEB DEVELOPMENT USING PHP"
    },
    {
      "REGNO": "202216080",
      "INT": 33.7,
      "UM": 40.0,
      "TOT": 74.0,
      "GRADE": "A",
      "SUBJECT": "CA1106A WEB DEVELOPMENT USING PHP"
    },
    {
      "REGNO": "202216081",
      "INT": 40.0,
      "UM": 46.0,
      "TOT": 86.0,
      "GRADE": "S",
      "SUBJECT": "CA1106A WEB DEVELOPMENT USING PHP"
    },
    {
      "REGNO": "202216082",
      "INT": 16.5,
      "UM": 10.75,
      "TOT": 28.0,
      "GRADE": "F",
      "SUBJECT": "CA1106A WEB DEVELOPMENT USING PHP"
    },
    {
      "REGNO": "202216083",
      "INT": 15.5,
      "UM": 1.0,
      "TOT": 17.0,
      "GRADE": "F",
      "SUBJECT": "CA1106A WEB DEVELOPMENT USING PHP"
    },
    {
      "REGNO": "202216084",
      "INT": 20.8,
      "UM": "AB",
      "TOT": 0.0,
      "GRADE": "I",
      "SUBJECT": "CA1106A WEB DEVELOPMENT USING PHP"
    },
    {
      "REGNO": "202216085",
      "INT": 11.1,
      "UM": 13.75,
      "TOT": 25.0,
      "GRADE": "F",
      "SUBJECT": "CA1106A WEB DEVELOPMENT USING PHP"
    },
    {
      "REGNO": "202216086",
      "INT": 35.05,
      "UM": 18.5,
      "TOT": 54.0,
      "GRADE": "C",
      "SUBJECT": "CA1106A WEB DEVELOPMENT USING PHP"
    },
    {
      "REGNO": "202216087",
      "INT": 20.7,
      "UM": 17.25,
      "TOT": 38.0,
      "GRADE": "E",
      "SUBJECT": "CA1106A WEB DEVELOPMENT USING PHP"
    },
    {
      "REGNO": "202216088",
      "INT": 36.0,
      "UM": 32.25,
      "TOT": 69.0,
      "GRADE": "B",
      "SUBJECT": "CA1106A WEB DEVELOPMENT USING PHP"
    },
    {
      "REGNO": "202216089",
      "INT": 31.6,
      "UM": 35.5,
      "TOT": 68.0,
      "GRADE": "B",
      "SUBJECT": "CA1106A WEB DEVELOPMENT USING PHP"
    },
    {
      "REGNO": "202216090",
      "INT": 14.0,
      "UM": 8.0,
      "TOT": 22.0,
      "GRADE": "F",
      "SUBJECT": "CA1106A WEB DEVELOPMENT USING PHP"
    },
    {
      "REGNO": "202216091",
      "INT": 21.25,
      "UM": 18.0,
      "TOT": 40.0,
      "GRADE": "E",
      "SUBJECT": "CA1106A WEB DEVELOPMENT USING PHP"
    },
    {
      "REGNO": "202216092",
      "INT": 15.0,
      "UM": 2.5,
      "TOT": 18.0,
      "GRADE": "F",
      "SUBJECT": "CA1106A WEB DEVELOPMENT USING PHP"
    }
  ]
}
